dloader/__init__.py
dloader/dataloader.py
dloader/py.typed
dloader-2025.7.dist-info/METADATA
dloader-2025.7.dist-info/WHEEL
dloader-2025.7.dist-info/licenses/LICENSE
dloader-2025.7.dist-info/RECORD
