Metadata-Version: 2.4
Name: dloader
Version: 2025.7
Summary: DataLoader implementation for Python asyncio
Project-URL: homepage, https://github.com/oinopion/dloader
Project-URL: repository, https://github.com/oinopion/dloader
Project-URL: documentation, https://oinopion.github.io/dloader/
Author-email: Tomek Paczkowski <tomek@hauru.eu>
License-Expression: MIT
License-File: LICENSE
Requires-Python: >=3.11
